{
    "levels": [
        {
            "id": 1,
            "title": "기초 회로 (5x5)",
            "description": "가장 기본적인 회로 복구 작업입니다. 주디와 함께 시작해보세요.",
            "size": 5,
            "answer": [
                [1, 1, 0, 0, 0],
                [1, 1, 0, 0, 0],
                [1, 1, 1, 1, 0],
                [0, 0, 1, 1, 0],
                [0, 0, 1, 1, 0]
            ],
            "blocks": [
                { "id": 1, "name": "ALPHA-2", "shape": [[1, 1], [1, 1]] },
                { "id": 2, "name": "BETA-4", "shape": [[1, 1, 1, 1]] },
                { "id": 3, "name": "GAMMA-2", "shape": [[1, 1], [1, 1]] }
            ]
        },
        {
            "id": 2,
            "title": "L자형 전송로 (5x5)",
            "description": "에너지 흐름이 꺾여 있습니다. 정확한 각도로 부품을 배치하세요.",
            "size": 5,
            "answer": [
                [1, 0, 0, 0, 0],
                [1, 0, 0, 0, 0],
                [1, 0, 0, 0, 0],
                [1, 1, 1, 1, 1],
                [0, 0, 0, 0, 0]
            ],
            "blocks": [
                { "id": 4, "name": "L-Long", "shape": [[1, 0], [1, 0], [1, 1]] },
                { "id": 5, "name": "I-Short", "shape": [[1, 1, 1, 1]] }
            ]
        },
        {
            "id": 3,
            "title": "중심 코어 (5x5)",
            "description": "중앙 집중형 회로입니다. 조각들이 겹치지 않게 주의하세요.",
            "size": 5,
            "answer": [
                [0, 0, 1, 0, 0],
                [0, 1, 1, 1, 0],
                [1, 1, 1, 1, 1],
                [0, 1, 1, 1, 0],
                [0, 0, 1, 0, 0]
            ],
            "blocks": [
                { "id": 6, "name": "T-Unit", "shape": [[1, 1, 1], [0, 1, 0]] },
                { "id": 7, "name": "I-Long", "shape": [[1, 1, 1, 1, 1]] },
                { "id": 8, "name": "T-Unit-B", "shape": [[1, 1, 1], [0, 1, 0]] },
                { "id": 9, "name": "P-Unit", "shape": [[1, 1], [1, 1]] }
            ]
        }
    ]
}
